area_splitter/__init__.py
area_splitter/__version__.py
area_splitter/db.py
area_splitter/splitter.py
area_splitter/algorithms/avg_building_voronoi.sql
area_splitter/algorithms/common/1-linear-features.sql
area_splitter/algorithms/common/2-group-buildings.sql
area_splitter/algorithms/common/3-cluster-buildings.sql
area_splitter/algorithms/common/4-algo
area_splitter/algorithms/common/5-simplify.sql
area_splitter/algorithms/common/6-alignment.sql
area_splitter/algorithms/common/7-extract.sql
area_splitter-3.0.1.dist-info/METADATA
area_splitter-3.0.1.dist-info/WHEEL
area_splitter-3.0.1.dist-info/licenses/LICENSE.md
area_splitter-3.0.1.dist-info/RECORD
