Metadata-Version: 2.4
Name: area-splitter
Version: 3.0.1
Summary: A utility for splitting an AOI into multiple tasks.
Project-URL: homepage, https://hotosm.github.io/fmtm-splitter
Project-URL: documentation, https://hotosm.github.io/fmtm-splitter
Project-URL: repository, https://github.com/hotosm/field-tm/blob/main/src/backend/packages/area-splitter
Author-email: Ivan Gayton <ivan.gayton@hotosm.org>, Rob Savoye <rob.savoye@hotosm.org>, Sam Woodcock <sam.woodcock@hotosm.org>, Sujan Adhikari <adhikarisujan.naxa@gmail.com>
License-Expression: GPL-3.0-only
License-File: LICENSE.md
Keywords: aoi,field-tm,hot,postgis,split
Classifier: Programming Language :: Python :: 3
Classifier: Programming Language :: Python :: 3.10
Classifier: Programming Language :: Python :: 3.11
Classifier: Programming Language :: Python :: 3.12
Classifier: Topic :: Scientific/Engineering :: GIS
Classifier: Topic :: Utilities
Requires-Python: >=3.10
Requires-Dist: geojson>=2.5.0
Requires-Dist: osm-rawdata>=0.2.2
Requires-Dist: psycopg>=3.1.17
Requires-Dist: shapely>=1.8.1
